README.md
pyproject.toml
src/res_msg/__init__.py
src/res_msg/cli.py
res_msg-0.3.2.dist-info/METADATA
res_msg-0.3.2.dist-info/WHEEL
res_msg-0.3.2.dist-info/entry_points.txt
res_msg-0.3.2.dist-info/RECORD
