Metadata-Version: 2.4
Name: res-msg
Version: 0.3.2
Summary: 一个简单的Python包，用于演示Python虚拟环境和包管理工具。
Requires-Python: >=3.12
Requires-Dist: requests>=2.32.3
Provides-Extra: dev
Requires-Dist: pytest-cov>=4.1.0; extra == 'dev'
Requires-Dist: pytest-mock>=3.12.0; extra == 'dev'
Requires-Dist: pytest>=8.0.0; extra == 'dev'
Requires-Dist: requests-mock>=1.11.0; extra == 'dev'
